[
{"Species":"Cod","Nova Scotia":"18,210","New Brunswick":"1,389","Prince Edward Island":"100","Quebec":"567","Newfoundland and Labrador":"1,108","British Columbia":"967"},
{"Species":"Haddock","Nova Scotia":"16,004","New Brunswick":"290","Prince Edward Island":"0","Quebec":"0","Newfoundland and Labrador":"142","British Columbia":"0"},
{"Species":"Redfish","Nova Scotia":"5,198","New Brunswick":"0","Prince Edward Island":"0","Quebec":"24","Newfoundland and Labrador":"3,211","British Columbia":"22,733"},
{"Species":"Halibut","Nova Scotia":"5,293","New Brunswick":"53","Prince Edward Island":"1","Quebec":"772","Newfoundland and Labrador":"1,036","British Columbia":"33,775"},
{"Species":"Flatfishes","Nova Scotia":"9,821","New Brunswick":"564","Prince Edward Island":"517","Quebec":"399","Newfoundland and Labrador":"1,059","British Columbia":"5,096"},
{"Species":"Greenland turbot","Nova Scotia":"1,591","New Brunswick":"46","Prince Edward Island":"0","Quebec":"3,575","Newfoundland and Labrador":"19,238","British Columbia":"1,178"},
{"Species":"Pollock","Nova Scotia":"6,998","New Brunswick":"324","Prince Edward Island":"0","Quebec":"0","Newfoundland and Labrador":"223","British Columbia":"965"},
{"Species":"Hake","Nova Scotia":"18,300","New Brunswick":"53","Prince Edward Island":"16","Quebec":"16","Newfoundland and Labrador":"240","British Columbia":"10,817"},
{"Species":"Cusk","Nova Scotia":"1,360","New Brunswick":"0","Prince Edward Island":"0","Quebec":"0","Newfoundland and Labrador":"1","British Columbia":"0"},
{"Species":"Catfish","Nova Scotia":"165","New Brunswick":"2","Prince Edward Island":"0","Quebec":"0","Newfoundland and Labrador":"67","British Columbia":"0"},
{"Species":"Skate","Nova Scotia":"731","New Brunswick":"0","Prince Edward Island":"4","Quebec":"4","Newfoundland and Labrador":"664","British Columbia":"321"},
{"Species":"Dogfish","Nova Scotia":"35","New Brunswick":"1","Prince Edward Island":"41","Quebec":"111","Newfoundland and Labrador":"3","British Columbia":"2,464"},
{"Species":"Herring","Nova Scotia":"16,517","New Brunswick":"15,273","Prince Edward Island":"5,244","Quebec":"2,388","Newfoundland and Labrador":"2,910","British Columbia":"77,372"},
{"Species":"Mackerel","Nova Scotia":"2,996","New Brunswick":"1,278","Prince Edward Island":"2,386","Quebec":"1,683","Newfoundland and Labrador":"1,349","British Columbia":"39"},
{"Species":"Swordfish","Nova Scotia":"5,819","New Brunswick":"0","Prince Edward Island":"0","Quebec":"0","Newfoundland and Labrador":"600","British Columbia":"0"},
{"Species":"Tuna","Nova Scotia":"12,438","New Brunswick":"0","Prince Edward Island":"915","Quebec":"0","Newfoundland and Labrador":"1,278","British Columbia":"2,665"},
{"Species":"Alewife","Nova Scotia":"628","New Brunswick":"441","Prince Edward Island":"28","Quebec":"0","Newfoundland and Labrador":"0","British Columbia":"0"},
{"Species":"Eel","Nova Scotia":"1,545","New Brunswick":"628","Prince Edward Island":"224","Quebec":"1,399","Newfoundland and Labrador":"579","British Columbia":"0"},
{"Species":"Salmon","Nova Scotia":"0","New Brunswick":"0","Prince Edward Island":"0","Quebec":"186","Newfoundland and Labrador":"299","British Columbia":"100,053"},
{"Species":"Smelt","Nova Scotia":"46","New Brunswick":"759","Prince Edward Island":"186","Quebec":"150","Newfoundland and Labrador":"7","British Columbia":"3"},
{"Species":"Capelin","Nova Scotia":"0","New Brunswick":"0","Prince Edward Island":"0","Quebec":"76","Newfoundland and Labrador":"6,273","British Columbia":"0"},
{"Species":"Oyster","Nova Scotia":"136","New Brunswick":"1,222","Prince Edward Island":"2,662","Quebec":"0","Newfoundland and Labrador":"0","British Columbia":"0"},
{"Species":"Scallop","Nova Scotia":"58,092","New Brunswick":"6,285","Prince Edward Island":"4,353","Quebec":"3,916","Newfoundland and Labrador":"18,166","British Columbia":"556"},
{"Species":"Squid","Nova Scotia":"660","New Brunswick":"0","Prince Edward Island":"0","Quebec":"0","Newfoundland and Labrador":"4,195","British Columbia":"151"},
{"Species":"Mussel","Nova Scotia":"0","New Brunswick":"170","Prince Edward Island":"0","Quebec":"171","Newfoundland and Labrador":"0","British Columbia":"0"},
{"Species":"Lobster","Nova Scotia":"204,045","New Brunswick":"61,843","Prince Edward Island":"64,975","Quebec":"33,335","Newfoundland and Labrador":"21,278","British Columbia":"0"},
{"Species":"Shrimp","Nova Scotia":"30,911","New Brunswick":"5,654","Prince Edward Island":"0","Quebec":"22,289","Newfoundland and Labrador":"83,945","British Columbia":"38,692"},
{"Species":"Crab, Queen","Nova Scotia":"27,545","New Brunswick":"53,794","Prince Edward Island":"5,336","Quebec":"60,205","Newfoundland and Labrador":"96,832","British Columbia":"0"},
{"Species":"Crab, Other","Nova Scotia":"2,476","New Brunswick":"890","Prince Edward Island":"791","Quebec":"344","Newfoundland and Labrador":"90","British Columbia":"24,195"},
{"Species":"Sea urchin","Nova Scotia":"3,417","New Brunswick":"4,024","Prince Edward Island":"0","Quebec":"146","Newfoundland and Labrador":"941","British Columbia":"11,972"}
]
